CausalPlayground/__init__.py
CausalPlayground/generators.py
CausalPlayground/scm.py
CausalPlayground/scm_environment.py
causal_playground-0.1.2.dist-info/LICENSE
causal_playground-0.1.2.dist-info/METADATA
causal_playground-0.1.2.dist-info/WHEEL
causal_playground-0.1.2.dist-info/top_level.txt
causal_playground-0.1.2.dist-info/RECORD
