Metadata-Version: 2.1
Name: causal-playground
Version: 0.1.2
Summary: Interactively generating causal data from structural causal models.
Author-email: Andreas Sauter <a.sauter@vu.nl>
License: MIT License
Project-URL: Homepage, https://sa-and.github.io/CausalPlayground/CausalPlayground.html
Project-URL: Documentation, https://sa-and.github.io/CausalPlayground/CausalPlayground.html
Project-URL: Repository, https://github.com/sa-and/CausalPlayground
Keywords: causality,reinforcement learning,structural causal model,data generation,RL,SCM
Classifier: Development Status :: 4 - Beta
Classifier: Programming Language :: Python :: 3.11
Classifier: Operating System :: OS Independent
Requires-Python: >=3.10
License-File: LICENSE
Requires-Dist: networkx >=3.2
Requires-Dist: dill
Requires-Dist: gymnasium
Requires-Dist: matplotlib
Requires-Dist: numpy
Requires-Dist: pandas
Requires-Dist: scipy
Requires-Dist: tqdm
